osada/__init__.py
osada/arrayFunc.py
osada/beep.py
osada/colorPrint.py
osada/mahjong.py
osada/mathFunc.py
osada/versionFunc.py
osada-1.2.1.dist-info/LICENSE
osada-1.2.1.dist-info/METADATA
osada-1.2.1.dist-info/WHEEL
osada-1.2.1.dist-info/top_level.txt
osada-1.2.1.dist-info/RECORD
