Metadata-Version: 2.1
Name: osada
Version: 1.2.1
Summary: Packed with features that the author, Osada, wants to use.
Home-page: https://github.com/Osada-M/osada
Author: OSADA Masashi
Author-email: osadamasashi.a@gmail.com
License: UNKNOWN
Platform: UNKNOWN
License-File: LICENSE
Requires-Dist: sounddevice (>=0.4.6)
